feather_db/core.cpython-313-darwin.so
feather_db-0.2.1.dist-info/licenses/LICENSE
feather_db-0.2.1.dist-info/METADATA
feather_db-0.2.1.dist-info/WHEEL
feather_db-0.2.1.dist-info/top_level.txt
feather_db-0.2.1.dist-info/RECORD
