Metadata-Version: 2.4
Name: feather-db
Version: 0.2.1
Summary: Fast, lightweight context-aware vector database - Part of Hawky.ai Digital Marketing OS
Author-email: "Hawky.ai Team" <hello@hawky.ai>
License: MIT
Project-URL: Homepage, https://www.getfeather.store/
Project-URL: Documentation, https://github.com/feather-store/feather/blob/main/README.md
Project-URL: Repository, https://github.com/feather-store/feather
Project-URL: Issues, https://github.com/feather-store/feather/issues
Project-URL: Changelog, https://github.com/feather-store/feather/blob/main/CHANGELOG.md
Project-URL: Hawky.ai, https://hawky.ai
Keywords: vector,database,similarity,search,embeddings,hnsw,ann,nearest-neighbor,machine-learning,ai
Classifier: Development Status :: 4 - Beta
Classifier: Intended Audience :: Developers
Classifier: Intended Audience :: Science/Research
Classifier: License :: OSI Approved :: MIT License
Classifier: Operating System :: OS Independent
Classifier: Programming Language :: Python :: 3
Classifier: Programming Language :: Python :: 3.8
Classifier: Programming Language :: Python :: 3.9
Classifier: Programming Language :: Python :: 3.10
Classifier: Programming Language :: Python :: 3.11
Classifier: Programming Language :: Python :: 3.12
Classifier: Programming Language :: C++
Classifier: Topic :: Database
Classifier: Topic :: Scientific/Engineering :: Artificial Intelligence
Classifier: Topic :: Software Development :: Libraries :: Python Modules
Requires-Python: >=3.8
License-File: LICENSE
Requires-Dist: numpy>=1.19.0
Provides-Extra: dev
Requires-Dist: pytest>=6.0; extra == "dev"
Requires-Dist: black>=21.0; extra == "dev"
Requires-Dist: flake8>=3.9; extra == "dev"
Provides-Extra: examples
Requires-Dist: sentence-transformers>=2.0; extra == "examples"
Dynamic: license-file
Dynamic: requires-python
